etflow/__init__.py
etflow/_version.py
etflow/eval.py
etflow/eval_cov_mat.py
etflow/eval_prop.py
etflow/eval_xl.py
etflow/train.py
etflow/utils.py
etflow/commons/__init__.py
etflow/commons/configs.py
etflow/commons/covmat.py
etflow/commons/featurization.py
etflow/commons/io.py
etflow/commons/sample.py
etflow/commons/utils.py
etflow/commons/xtb.py
etflow/data/__init__.py
etflow/data/datamodule.py
etflow/data/dataset.py
etflow/data/geom.py
etflow/models/__init__.py
etflow/models/base.py
etflow/models/loss.py
etflow/models/model.py
etflow/models/utils.py
etflow/networks/__init__.py
etflow/networks/torchmd_net/__init__.py
etflow/networks/torchmd_net/model_dynamics.py
etflow/networks/torchmd_net/modules.py
etflow/networks/torchmd_net/utils.py
etflow/schedulers/CosineAnnealingWarmRestarts.py
etflow/schedulers/__init__.py
etflow-0.1.2.dist-info/LICENSE
etflow-0.1.2.dist-info/METADATA
etflow-0.1.2.dist-info/WHEEL
etflow-0.1.2.dist-info/top_level.txt
etflow-0.1.2.dist-info/RECORD
