Metadata-Version: 2.1
Name: etflow
Version: 0.1.2
Summary: Equivariant Flow Matching for Molecular Conformer Generation
Author-email: Majdi Hassan <majdi.hassan@mila.quebec>, Nikhil Shenoy <nikhilshenoy98@gmail.com>, Jungyoon Lee <jungyoon.lee@mila.quebec>, Hannes Stark <hstark@mit.edu>, Stephan Thaler <stephan@valencelabs.com>, Dominique Beaini <dominique@valencelabs.com>
License: MIT
Classifier: Development Status :: 4 - Beta
Classifier: Intended Audience :: Developers
Classifier: Intended Audience :: Science/Research
Classifier: Topic :: Scientific/Engineering :: Artificial Intelligence
Classifier: Topic :: Scientific/Engineering :: Bio-Informatics
Classifier: Topic :: Scientific/Engineering :: Information Analysis
Classifier: Topic :: Scientific/Engineering :: Medical Science Apps.
Classifier: Natural Language :: English
Classifier: Operating System :: OS Independent
Classifier: Programming Language :: Python
Classifier: Programming Language :: Python :: 3
Classifier: Programming Language :: Python :: 3.8
Classifier: Programming Language :: Python :: 3.9
Classifier: Programming Language :: Python :: 3.10
Classifier: Programming Language :: Python :: 3.11
Classifier: Programming Language :: Python :: 3.12
Requires-Python: >=3.8
License-File: LICENSE
Requires-Dist: tqdm
Requires-Dist: pydantic
Requires-Dist: fsspec
Requires-Dist: pandas
Requires-Dist: scipy
Requires-Dist: numpy==1.26.4
Requires-Dist: datamol
Requires-Dist: rdkit
Requires-Dist: py3Dmol
Requires-Dist: torch
Requires-Dist: torch-geometric
Requires-Dist: lightning
Requires-Dist: torchmetrics
Requires-Dist: torch-cluster
Requires-Dist: wandb
Requires-Dist: matplotlib
Requires-Dist: seaborn
